bias_rank_component/__init__.py
bias_rank_component/frontend/build/asset-manifest.json
bias_rank_component/frontend/build/bootstrap.min.css
bias_rank_component/frontend/build/index.html
bias_rank_component/frontend/build/precache-manifest.cc24608f61aac9ed71ab1eb92764cb2a.js
bias_rank_component/frontend/build/service-worker.js
bias_rank_component/frontend/build/static/js/2.da1f79ce.chunk.js
bias_rank_component/frontend/build/static/js/2.da1f79ce.chunk.js.LICENSE.txt
bias_rank_component/frontend/build/static/js/2.da1f79ce.chunk.js.map
bias_rank_component/frontend/build/static/js/main.f648ff23.chunk.js
bias_rank_component/frontend/build/static/js/main.f648ff23.chunk.js.map
bias_rank_component/frontend/build/static/js/runtime-main.44d30fc2.js
bias_rank_component/frontend/build/static/js/runtime-main.44d30fc2.js.map
streamlit_bias_rank_component-0.0.1.dist-info/LICENSE
streamlit_bias_rank_component-0.0.1.dist-info/METADATA
streamlit_bias_rank_component-0.0.1.dist-info/WHEEL
streamlit_bias_rank_component-0.0.1.dist-info/top_level.txt
streamlit_bias_rank_component-0.0.1.dist-info/RECORD
