Metadata-Version: 2.1
Name: streamlit-bias-rank-component
Version: 0.0.1
Summary: UNKNOWN
Home-page: UNKNOWN
Author: Rafal Kocielnik
Author-email: 
License: UNKNOWN
Platform: UNKNOWN
Requires-Python: >=3.6
Requires-Dist: streamlit (>=0.63)
